whisk/__init__.py
whisk/whisk_utils.py
whisk/bin/classify
whisk/bin/classify-single-whisker
whisk/bin/classify-single-whisker.exe
whisk/bin/classify-single-whisker.exp
whisk/bin/classify-single-whisker.ilk
whisk/bin/classify-single-whisker.lib
whisk/bin/classify.exe
whisk/bin/classify.exp
whisk/bin/classify.ilk
whisk/bin/classify.lib
whisk/bin/classify_radial
whisk/bin/classify_radial.exe
whisk/bin/classify_radial.exp
whisk/bin/classify_radial.ilk
whisk/bin/classify_radial.lib
whisk/bin/libtraj.so
whisk/bin/libwhisk.so
whisk/bin/libwhiskio.so
whisk/bin/measure
whisk/bin/measure.exe
whisk/bin/measure.exp
whisk/bin/measure.ilk
whisk/bin/measure.lib
whisk/bin/measurements_convert
whisk/bin/measurements_convert.exe
whisk/bin/measurements_convert.exp
whisk/bin/measurements_convert.ilk
whisk/bin/measurements_convert.lib
whisk/bin/mexLoadMeasurements.mexa64
whisk/bin/mexLoadMeasurements.mexw64
whisk/bin/mexLoadWhiskers.mexa64
whisk/bin/mexLoadWhiskers.mexw64
whisk/bin/mexSaveMeasurements.mexa64
whisk/bin/mexSaveMeasurements.mexw64
whisk/bin/mexSaveWhiskers.mexa64
whisk/bin/mexSaveWhiskers.mexw64
whisk/bin/preprocess
whisk/bin/preprocess.exe
whisk/bin/preprocess.exp
whisk/bin/preprocess.ilk
whisk/bin/preprocess.lib
whisk/bin/reclassify
whisk/bin/reclassify.exe
whisk/bin/reclassify.exp
whisk/bin/reclassify.ilk
whisk/bin/reclassify.lib
whisk/bin/report
whisk/bin/report.exe
whisk/bin/report.exp
whisk/bin/report.ilk
whisk/bin/report.lib
whisk/bin/seedtest
whisk/bin/seedtest.exe
whisk/bin/seedtest.exp
whisk/bin/seedtest.ilk
whisk/bin/seedtest.lib
whisk/bin/stripetest
whisk/bin/stripetest.exe
whisk/bin/stripetest.exp
whisk/bin/stripetest.ilk
whisk/bin/stripetest.lib
whisk/bin/test_eval_2.exe
whisk/bin/test_eval_2.exp
whisk/bin/test_eval_2.ilk
whisk/bin/test_eval_2.lib
whisk/bin/test_eval_3.exe
whisk/bin/test_eval_3.exp
whisk/bin/test_eval_3.ilk
whisk/bin/test_eval_3.lib
whisk/bin/test_eval_4.exe
whisk/bin/test_eval_4.exp
whisk/bin/test_eval_4.ilk
whisk/bin/test_eval_4.lib
whisk_janelia-1.1.10.dist-info/LICENSE.txt
whisk_janelia-1.1.10.dist-info/METADATA
whisk_janelia-1.1.10.dist-info/WHEEL
whisk_janelia-1.1.10.dist-info/top_level.txt
whisk_janelia-1.1.10.dist-info/RECORD
