Metadata-Version: 2.1
Name: whisk-janelia
Version: 1.1.10
Summary: Fully automated tracking of single rows of whiskers in high-speed video.
Home-page: https://github.com/nclack/whisk/
Author: Nathan Clack
Maintainer: clackn, cxrodgers, mitchclough, vncntprvst
License: LICENSE.txt
License-File: LICENSE.txt
Provides-Extra: ffmpeg
Requires-Dist: requests <3,>=2.24 ; extra == 'ffmpeg'
